BL_Python/development/__init__.py
BL_Python/development/profiling.py
BL_Python.development-0.2.0.dist-info/LICENSE.md
BL_Python.development-0.2.0.dist-info/METADATA
BL_Python.development-0.2.0.dist-info/WHEEL
BL_Python.development-0.2.0.dist-info/top_level.txt
BL_Python.development-0.2.0.dist-info/RECORD
