Metadata-Version: 2.1
Name: BL_Python.development
Version: 0.2.0
Summary: Utilities and tools for assisting in development of software.
Author-email: Aaron Holmes <aholmes@mednet.ucla.edu>
Project-URL: Homepage, https://github.com/uclahs-cds/BL_Python
Project-URL: Bug Tracker, https://github.com/uclahs-cds/BL_Python/issues
Project-URL: Repository, https://github.com/uclahs-cds/BL_Python.git
Project-URL: Changelog, https://github.com/uclahs-cds/BL_Python/blob/main/CHANGELOG.md
Classifier: Programming Language :: Python :: 3
Classifier: License :: OSI Approved :: GNU General Public License (GPL)
Classifier: Operating System :: OS Independent
Classifier: Topic :: Scientific/Engineering
Classifier: Topic :: Software Development :: Libraries
Classifier: Topic :: Software Development :: Libraries :: Application Frameworks
Classifier: Intended Audience :: Science/Research
Classifier: Intended Audience :: Developers
Classifier: Development Status :: 4 - Beta
Classifier: Natural Language :: English
Requires-Python: >=3.10
License-File: LICENSE.md
